[{"state_id":844,"id":63255,"name":"Arida Shi"},{"state_id":844,"id":63388,"name":"Gobō"},{"state_id":844,"id":63444,"name":"Hashimoto"},{"state_id":844,"id":63445,"name":"Hashimoto Shi"},{"state_id":844,"id":63618,"name":"Iwade"},{"state_id":844,"id":63619,"name":"Iwade Shi"},{"state_id":844,"id":63662,"name":"Kainan"},{"state_id":844,"id":63663,"name":"Kainan Shi"},{"state_id":844,"id":63788,"name":"Kinokawa Shi"},{"state_id":844,"id":63904,"name":"Kōya"},{"state_id":844,"id":63973,"name":"Minato"},{"state_id":844,"id":64339,"name":"Shingū"},{"state_id":844,"id":64341,"name":"Shingū-shi"},{"state_id":844,"id":64464,"name":"Tanabe-shi"},{"state_id":844,"id":64616,"name":"Wakayama"},{"state_id":844,"id":64617,"name":"Wakayama Shi"}]