[{"country_id":11,"id":4880,"name":"Autonomous City Of Buenos Aires"},{"country_id":11,"id":3656,"name":"Buenos Aires Province"},{"country_id":11,"id":3647,"name":"Catamarca Province"},{"country_id":11,"id":3640,"name":"Chaco Province"},{"country_id":11,"id":3651,"name":"Chubut Province"},{"country_id":11,"id":3642,"name":"Córdoba Province"},{"country_id":11,"id":3638,"name":"Corrientes"},{"country_id":11,"id":3654,"name":"Entre Ríos Province"},{"country_id":11,"id":3652,"name":"Formosa Province"},{"country_id":11,"id":3645,"name":"Jujuy Province"},{"country_id":11,"id":3655,"name":"La Pampa"},{"country_id":11,"id":3653,"name":"La Rioja Province"},{"country_id":11,"id":3646,"name":"Mendoza"},{"country_id":11,"id":3644,"name":"Misiones Province"},{"country_id":11,"id":3648,"name":"Neuquén Province"},{"country_id":11,"id":3639,"name":"Río Negro Province"},{"country_id":11,"id":3643,"name":"Salta Province"},{"country_id":11,"id":3634,"name":"San Juan Province"},{"country_id":11,"id":3636,"name":"San Luis Province"},{"country_id":11,"id":3649,"name":"Santa Cruz Province"},{"country_id":11,"id":3641,"name":"Santa Fe Province"},{"country_id":11,"id":3635,"name":"Santiago del Estero Province"},{"country_id":11,"id":3650,"name":"Tierra del Fuego Province"},{"country_id":11,"id":3637,"name":"Tucumán Province"}]